flamingo/__init__.py
flamingo/__version__.py
flamingo/cat_interface.py
flamingo/log_config.py
flamingo/py.typed
flamingo/schemas.py
flamingo/screen.py
flamingo/utils.py
flamingo/data/scscore/full_reaxys_model_1024bool/model.ckpt-10654.as_numpy.json.gz
flamingo/data/scscore/full_reaxys_model_2048bool/model.ckpt-10654.as_numpy.json.gz
flamingo/features/__init__.py
flamingo/features/featurizer.py
flamingo/models/__init__.py
flamingo/models/scscore.py
nlesc_flamingo-0.3.0.data/data/citation/flamingo/CITATION.cff
tests/__init__.py
tests/test_build.py
tests/test_cat_interface.py
tests/test_filter.py
tests/test_hdf5.py
tests/test_logger.py
tests/test_mypy.py
tests/test_options.py
tests/test_scscore.py
tests/test_sphinx.py
tests/utils_test.py
nlesc_flamingo-0.3.0.dist-info/LICENSE
nlesc_flamingo-0.3.0.dist-info/METADATA
nlesc_flamingo-0.3.0.dist-info/WHEEL
nlesc_flamingo-0.3.0.dist-info/entry_points.txt
nlesc_flamingo-0.3.0.dist-info/top_level.txt
nlesc_flamingo-0.3.0.dist-info/RECORD
