Metadata-Version: 2.1
Name: nlesc-flamingo
Version: 0.3.0
Summary: Compute and filter molecular properties
Home-page: https://github.com/https://github.com/nlesc-nano/flamingo
Author: Felipe Zapata
Author-email: f.zapata@esciencecenter.nl
License: Apache Software License 2.0
Keywords: flamingo
Platform: UNKNOWN
Classifier: Development Status :: 4 - Beta
Classifier: Intended Audience :: Science/Research
Classifier: Intended Audience :: Developers
Classifier: License :: OSI Approved :: Apache Software License
Classifier: Natural Language :: English
Classifier: Programming Language :: Python :: 3
Classifier: Programming Language :: Python :: 3.7
Classifier: Programming Language :: Python :: 3.8
Classifier: Programming Language :: Python :: 3.9
Classifier: Typing :: Typed
Requires-Python: >=3.7
Requires-Dist: nlesc-CAT (>=0.10.0)
Requires-Dist: nano-CAT (>=0.7.0)
Requires-Dist: data-CAT (>=0.7.0)
Requires-Dist: plams (>=1.5.1)
Requires-Dist: more-itertools
Requires-Dist: numpy
Requires-Dist: pandas
Requires-Dist: pyyaml (>=5.1.1)
Requires-Dist: schema (!=0.7.5)
Requires-Dist: typing-extensions
Requires-Dist: h5py
Provides-Extra: doc
Requires-Dist: sphinx ; extra == 'doc'
Requires-Dist: sphinx-autodoc-typehints ; extra == 'doc'
Requires-Dist: sphinx-rtd-theme ; extra == 'doc'
Requires-Dist: nbsphinx ; extra == 'doc'
Provides-Extra: test
Requires-Dist: coverage ; extra == 'test'
Requires-Dist: mypy ; extra == 'test'
Requires-Dist: pycodestyle ; extra == 'test'
Requires-Dist: pytest (>=3.9) ; extra == 'test'
Requires-Dist: pytest-cov ; extra == 'test'
Requires-Dist: pytest-mock ; extra == 'test'
